source_coop/__init__.py
source_coop/api.py
source_coop/auth.py
source_coop/cli.py
source_coop/client.py
source_coop/s3.py
source_coop/commands/__init__.py
source_coop/commands/download.py
source_coop/commands/login.py
source_coop/commands/members.py
source_coop/commands/profile.py
source_coop/commands/repos.py
source_coop/commands/summarize.py
source_coop/commands/whoami.py
source_coop-0.1.0.data/data/LICENSE
source_coop-0.1.0.dist-info/licenses/LICENSE
source_coop-0.1.0.dist-info/METADATA
source_coop-0.1.0.dist-info/WHEEL
source_coop-0.1.0.dist-info/entry_points.txt
source_coop-0.1.0.dist-info/top_level.txt
source_coop-0.1.0.dist-info/RECORD
