Metadata-Version: 2.4
Name: source-coop
Version: 0.1.0
Summary: Unofficial Python SDK & CLI for Source Coop
Home-page: https://github.com/samapriya/source-coop
Author: Samapriya Roy
Author-email: samapriya.roy@gmail.com
License: Apache 2.0
Classifier: Development Status :: 3 - Alpha
Classifier: Intended Audience :: Developers
Classifier: License :: OSI Approved :: Apache Software License
Classifier: Programming Language :: Python :: 3
Classifier: Programming Language :: Python :: 3.7
Classifier: Programming Language :: Python :: 3.8
Classifier: Operating System :: OS Independent
Requires-Python: >=3.7
License-File: LICENSE
Requires-Dist: requests>=2.25.0
Requires-Dist: boto3>=1.17.0
Requires-Dist: rich>=10.0.0
Requires-Dist: pandas>=1.0.0
Requires-Dist: pyarrow>=3.0.0
Requires-Dist: tqdm>=4.60.0
Requires-Dist: aiohttp>=3.8.0
Requires-Dist: aiofiles>=0.7.0
Dynamic: author
Dynamic: author-email
Dynamic: classifier
Dynamic: description
Dynamic: description-content-type
Dynamic: home-page
Dynamic: license
Dynamic: license-file
Dynamic: requires-dist
Dynamic: requires-python
Dynamic: summary
